more.pony-0.4-py3.11-nspkg.pth
more/pony/__init__.py
more/pony/app.py
more/pony/tests/test_pony.py
more.pony-0.4.dist-info/LICENSE.txt
more.pony-0.4.dist-info/METADATA
more.pony-0.4.dist-info/WHEEL
more.pony-0.4.dist-info/namespace_packages.txt
more.pony-0.4.dist-info/top_level.txt
more.pony-0.4.dist-info/RECORD
