Metadata-Version: 2.1
Name: more.pony
Version: 0.4
Summary: Pony ORM integration in Morepath
Home-page: https://github.com/morepath/more.pony
Author: Henri Hulski
Author-email: henri.hulski@gazeta.pl
License: BSD
Keywords: morepath Pony ORM PonyORM
Classifier: Intended Audience :: Developers
Classifier: License :: OSI Approved :: BSD License
Classifier: Programming Language :: Python :: 3.8
Classifier: Programming Language :: Python :: 3.9
Classifier: Programming Language :: Python :: 3.10
Classifier: Programming Language :: Python :: 3.11
Classifier: Programming Language :: Python :: Implementation :: PyPy
License-File: LICENSE.txt
Requires-Dist: morepath >=0.19
Requires-Dist: pony >=0.7.17
Provides-Extra: coverage
Requires-Dist: pytest-cov ; extra == 'coverage'
Provides-Extra: lint
Requires-Dist: flake8 ; extra == 'lint'
Requires-Dist: black ; extra == 'lint'
Provides-Extra: test
Requires-Dist: pytest >=2.9.1 ; extra == 'test'
Requires-Dist: pytest-remove-stale-bytecode ; extra == 'test'
Requires-Dist: webtest ; extra == 'test'
Requires-Dist: pygments ; extra == 'test'
